{
    "question-1": "C",
    "question-2": "D",
    "question-3": "A",
    "question-4": "C",
    "question-5": "A",
    "question-6": "C",
    "question-7": "C",
    "question-8": "C",
    "question-9": "C",
    "question-10": "D",
    "question-11": "A",
    "question-12": "C",
    "question-13": "C",
    "question-14": "C",
    "question-15": "A",
    "question-16": "B",
    "question-17": "C",
    "question-18": "B",
    "question-19": "B",
    "question-20": "D",
    "question-21": "A",
    "question-22": "C",
    "question-23": "C",
    "question-24": "A",
    "question-25": "D",
    "question-26": "A",
    "question-27": "A",
    "question-28": "B",
    "question-29": "C",
    "question-30": "D"
}
